{
  "PowerAttackBash": 3924,
  "MagicNoDistintegrate": 3807,
  "NoDecapitate": 95264,
  "ImmuneStrongUnrelentingForce": 94892,
  "MQSovngardeSparringKeyword": 94276,
  "C01Companion": 1113874,
  "ArmorDarkBrotherhood": 1113442,
  "ArmorNightingale": 1113441,
  "MagicAlchDamageMagicka": 1112542,
  "MagicAlchDamageHealth": 1112541,
  "MagicAlchDamageStamina": 1112540,
  "MQ201ThalmorDisguise": 1111522,
  "CWHornLink": 1109519,
  "MQ105GreybeardCallKeyword": 1109090,
  "MagicAlchResistPoison": 1108831,
  "ActorTypeFamiliar": 1108695,
  "ActorTypeGiant": 1108356,
  "dunCGMagicLightFire": 1107124,
  "dunCGMagicHeavyFire": 1107123,
  "LinkBlowHorn": 1106928,
  "MagicWeaponSpeed": 1106612,
  "WeapTypeBoundArrow": 1103105,
  "ClothingHands": 1101075,
  "ClothingFeet": 1101074,
  "ClothingHead": 1101073,
  "ClothingNecklace": 1101066,
  "ClothingRing": 1101065,
  "ClothingCirclet": 1101064,
  "CWDiplomaticVictory": 1099249,
  "UpdateDuringArchery": 1098819,
  "MQHighHrothgarTrainingKeyword": 1097795,
  "isHadvarWriteLedger": 1092777,
  "WeapMaterialSilver": 1092122,
  "MagicRune": 1088889,
  "GoalLink": 1088600,
  "MagicTrapPoison": 1086395,
  "MQSkyHavenSparringKeyword": 1086180,
  "MagicSummonFamiliar": 1085903,
  "DragonsreachPorchPatrol": 1082009,
  "MustStop": 1081435,
  "LinkCarriageSeat": 1079041,
  "LinkCarriageHorse": 1079040,
  "MagicSchoolConjuration": 1079028,
  "MagicSchoolRestoration": 1079027,
  "MagicSchoolIllusion": 1079026,
  "MagicSchoolAlteration": 1079025,
  "MagicSchoolDestruction": 1079024,
  "CWMission03ImperialGarb": 1078788,
  "CWMission03StormcloakGarb": 1078787,
  "isJarlChair": 1074459,
  "isPullChain": 1074452,
  "MQClearSkyFogEffect02Kywd": 1074051,
  "MQClearSkyFogEffect01Kywd": 1074049,
  "isHorseCartTravel": 1072459,
  "isWallCornerPeekR": 1069722,
  "isWallCornerPeekL": 1069712,
  "isMeadBarrel": 1069708,
  "TwoStateCollisionKeyword": 1069541,
  "MagicArmor70Perk": 1067704,
  "MagicArmor50Perk": 1067703,
  "MagicArmor30Perk": 1067702,
  "NoSoulTrap": 1063634,
  "MammothFollowerKeyword03": 1063084,
  "MammothFollowerKeyword02": 1063083,
  "MammothFollowerKeyword01": 1063082,
  "isCartTravelPlayer": 1061956,
  "isCartTravelDriver": 1061955,
  "WERoadStart": 1058726,
  "WerewolfCeremony": 1056785,
  "MagicVampireDrain": 1055710,
  "isNocturnal": 1055348,
  "isWerewolfEscape": 1054955,
  "isSmallCookingPotDBPoison": 1052853,
  "isSmallCookingPot": 1052850,
  "isNirnroot": 1052849,
  "MagicEnchResistDisease": 1052257,
  "LocSetCaveIce": 1050649,
  "WerewolfCanActivate": 1050473,
  "MagicEnchResistPoison": 1048225,
  "MagicNoInvisibility": 1048224,
  "VendorNoSale": 1047035,
  "CWSiegeRunning": 1039409,
  "isVampireCoffin": 1039337,
  "RaceToScale": 1036513,
  "RaceUseGeometryEmitterForParticles": 1035607,
  "LocTypePlayerHouse": 1032611,
  "DB10MagicLightFire": 1032175,
  "DB10MagicHeavyFire": 1032174,
  "isMQ206FelldirRitual": 1030750,
  "MagicBlessing": 1030540,
  "MagicRestedStamina": 1030535,
  "MagicRestedMagicka": 1030534,
  "MagicRestedHealth": 1030533,
  "BardPlaySpot": 1030405,
  "AmbushSpiderLarge": 1018461,
  "AmbushSpiderSmall": 1018460,
  "AmbushSpiderGiant": 1018459,
  "MagicAlchDurationBased": 1018447,
  "MagicAlchBeneficial": 1018446,
  "NoDetectLife": 1016564,
  "MagicDamageResist": 1016291,
  "isTorchLighting": 1012168,
  "isTG06TranslateBook": 1010896,
  "IsGreybeardMeditate": 1009806,
  "LocTypeClearable": 1007232,
  "dunMossMotherDaggerKeyword": 1006896,
  "ActorTypeTroll": 1006870,
  "VendorItemRecipe": 1006768,
  "IsMQ203Table": 1005714,
  "isBarCounter": 1003640,
  "dunTreasMap": 1001983,
  "CraftingSmithingSkyforge": 1001166,
  "CWPhaseBehind": 999040,
  "Dummy": 999020,
  "isDA02BoethiahPost": 998244,
  "ImmuneParalysis": 992197,
  "SpouseBedKeyword": 989159,
  "isIdleBlessingKneel": 987632,
  "isIdlePrayCrouched": 987624,
  "isWalkThroughWall": 985597,
  "CWLinkFieldCOEnable": 983098,
  "isSearchingChest": 982131,
  "isSearchingTable": 982130,
  "isAltarOfMolagBal": 981327,
  "isTG08Ceremony": 974652,
  "FarmerNirnroot": 974614,
  "FarmerCabbage": 974613,
  "FarmerGourd": 974612,
  "FarmerLeek": 974611,
  "FarmerPotato": 974610,
  "FarmerWheat": 974609,
  "ReusableSoulGem": 971505,
  "isExecutionerGuard": 964108,
  "isBlacksmithAnvil": 964107,
  "isWritingChair": 961099,
  "isWritingTable": 959292,
  "isKneeling": 953935,
  "BookShelfTrigger04": 951566,
  "BookShelfTrigger03": 951553,
  "BookShelfTrigger01": 951552,
  "CWLostByTreaty": 946779,
  "CWLinkGuardNONE": 922497,
  "CWMission07TargetLink2": 909627,
  "CWMission07TargetLink1": 909622,
  "CWMission07AimLink": 909621,
  "RidingInCarriage": 906801,
  "isTGFalmerStatue": 900674,
  "LinkCartStartingLocation": 890135,
  "isBlacksmithWorkbench": 889646,
  "IsWounded03": 886593,
  "IsWounded02": 886592,
  "IsWounded01": 886591,
  "isWoundedFloorMarker": 886583,
  "isAltar": 879669,
  "IsBeastRace": 877009,
  "BookShelfBook18": 875568,
  "BookShelfBook17": 875567,
  "BookShelfBook16": 875566,
  "BookShelfBook15": 875565,
  "BookShelfBook14": 875487,
  "BookShelfBook13": 875434,
  "BookShelfBook12": 875410,
  "BookShelfBook11": 875409,
  "BookShelfBook10": 875408,
  "BookShelfBook09": 875407,
  "BookShelfBook08": 875406,
  "BookShelfBook07": 875405,
  "BookShelfBook06": 875404,
  "BookShelfBook05": 875403,
  "BookShelfBook04": 875402,
  "BookShelfBook03": 875401,
  "BookShelfBook02": 875400,
  "BookShelfBook01": 875399,
  "BookShelfFirstBook": 875228,
  "BookShelfLastBook": 875200,
  "BookShelfContainer": 875198,
  "BookShelfTrigger02": 875196,
  "BookShelfClickTrigger": 875155,
  "MS11InvestigationBlockActivation": 873974,
  "MS11InvestigationObjectLink": 873973,
  "CWSiegePlayerRanAway": 844391,
  "BladesRecruitKeyword": 817382,
  "MQ206FriendDistractionKeyword": 812285,
  "isIdleSoldierWall": 785159,
  "VendorItemFireword": 781527,
  "MQResurrectDragonKeyword": 735651,
  "Testchic": 731207,
  "CRReconKicker": 716708,
  "CraftingSmithingArmorTable": 711544,
  "MagicNightEye": 710598,
  "C01AmbushTightMarker": 683905,
  "C01AmbushWideMarker": 683904,
  "CraftingSmelter": 679118,
  "CraftingCookpot": 679091,
  "WIRentRoomWalkToStart": 670796,
  "SolitudeOpeningSceneMarker": 670692,
  "isGrainMill": 640734,
  "isSmelter": 640707,
  "PlayerKeyword": 627462,
  "CW0MeleeClose": 624070,
  "linkSisterSwitch": 596096,
  "isCookingSpit": 428762,
  "WICraftingSmithingTempering": 325373,
  "WICraftingAlchemy": 325350,
  "WICraftingEnchanting": 325341,
  "WICraftingSmithing": 325248,
  "isAlchemy": 173067,
  "BarredDoorNavCutKeyword": 534693,
  "LinkDragonLandingMarker": 527150,
  "isHideL": 500317,
  "MagicVoiceChangeWeather": 498447,
  "WIDragonAttacked": 498412,
  "CraftingTanningRack": 493162,
  "isTanning": 468896,
  "isEnchanting": 451235,
  "MQ201ThalmorEmbassyGuard": 439215,
  "isHideR": 409385,
  "isPickaxeTable": 398249,
  "isPickaxeFloor": 398248,
  "BardSongsKeyword": 290851,
  "PerkQuickReflexesKeyword": 289715,
  "MQClearSkiesFogTrigger": 276749,
  "WIDragonsToggle": 272528,
  "Favor018TargetLocation": 259269,
  "ShoutFireBreath": 950908,
  "isLadder": 938391,
  "FurnitureBedRoll": 936662,
  "CWNeutral": 921004,
  "dunCGStructure": 890399,
  "dunCGClutter": 890398,
  "dunCGFX": 890397,
  "FurnitureDBShelf": 883451,
  "ArenaCombatWave5": 874057,
  "ArenaCombatWave4": 874056,
  "ArenaCombatWave3": 874055,
  "ArenaCombatWave2": 874054,
  "ArenaCombatWave1": 874053,
  "ArenaCombatantDoorLink": 874052,
  "ActorTypeGhost": 860254,
  "CWFinaleStart": 857167,
  "MagicSprigganCallAnimals": 847380,
  "C06CompanionsGhostsKeyword": 844184,
  "BQActiveQuest": 834201,
  "CWEventHappening": 831323,
  "isBlacksmithForge": 830986,
  "CWFortSiegeMinorCapitalStart": 829504,
  "minionlink02": 819194,
  "minionLink01": 819193,
  "CWFortBarricadeMutualDistructionLink": 812843,
  "CWHQ": 812838,
  "MagicThrallHealthRegen": 810001,
  "WeapMaterialFalmerHoned": 809988,
  "WeapMaterialFalmer": 809987,
  "WeapMaterialDraugrHoned": 809986,
  "WeapMaterialDraugr": 809985,
  "WeapMaterialImperial": 809984,
  "isSitCrossLegged": 806652,
  "isLeanTable": 806642,
  "WIComplexInteractionToggle": 806600,
  "CWLinkFieldCOBed": 805526,
  "CWLinkFieldCOMap": 805525,
  "CWLinkFortSandbox": 805506,
  "isLayDown": 804911,
  "isSitLedge": 804902,
  "isShackleWall": 804895,
  "MagicInfluenceFrenzy": 804022,
  "isHammerWall": 803626,
  "isHammerTable": 803625,
  "MagicDisallowEnchanting": 796605,
  "PerkDarkSouls": 794255,
  "CombatOverrideLink": 786556,
  "CRRecon": 785532,
  "CompanionsRadiantQuestStart": 785525,
  "isPickaxeWall": 688835,
  "Vampire": 688827,
  "MinerQuicksilver": 688147,
  "MinerMalachite": 688146,
  "MinerMoonstone": 688145,
  "MinerGold": 688144,
  "MinerEbony": 688143,
  "MinerCorundum": 688142,
  "MinerSilver": 688141,
  "MinerOrichalcum": 688140,
  "MinerIron": 688139,
  "LocTypeHabitationHasInn": 683652,
  "StormCallKeyword": 662106,
  "BoundCaptive": 661984,
  "FavorOrcsIntroKeyword": 484304,
  "dunIronbindGoalBeemJa": 421963,
  "dunIronbindGoalSalma": 421907,
  "CWCitizensFleeStart": 410448,
  "FurnitureLedgeSit": 162458,
  "ClearSkiesKeyword": 123824,
  "BucketPour": 123766,
  "BucketFill": 123319,
  "FloraFlower": 104742,
  "CWFortSiegeSpecialStart": 99205,
  "MGRitualSummon": 630603,
  "FurnitureLayDownMarker": 575349,
  "havokDisabledPartner": 568745,
  "CraftTypeCookpot": 544029,
  "LinkCarryEnd": 498362,
  "LinkCarryStart": 498361,
  "isBarStool": 478919,
  "isExecutioner": 461834,
  "CWLinkPatrolFollow2": 381197,
  "CWLinkPatrolFollow1": 381196,
  "WIDragonKilledStart": 330981,
  "WIGamesHideAndSeekStart": 309354,
  "FurnitureExecutioner": 190701,
  "PerkFistsDwarven": 180605,
  "PerkFistsDaedric": 180603,
  "PerkFistsDragonplate": 180602,
  "PerkFistsSteelPlate": 180601,
  "PerkFistsEbony": 180600,
  "PerkFistsOrcish": 180599,
  "MagicTurnUndead": 776255,
  "Movable": 773878,
  "WoodPickUp": 768344,
  "MS13ClawKeyword": 760864,
  "JobHireling": 760190,
  "LinkCustom10": 759046,
  "LinkCustom09": 759045,
  "LinkCustom08": 759044,
  "LinkCustom07": 759043,
  "LinkCustom06": 759042,
  "FurntiureNoPlayerAnim": 753075,
  "MagicSlow": 750238,
  "MagicCloak": 746212,
  "TrainingTarget": 740442,
  "FavorSimpleDrunksSceneKeyword": 721523,
  "WIGamesTagStart": 712709,
  "ArmorMaterialStormcloak": 704826,
  "LinkWaitUntilTriggered": 698642,
  "linkWaitPoint": 698638,
  "MagicFortifyTwoHanded": 696362,
  "MagicFortifyOneHanded": 696361,
  "WISpellDangerous": 695071,
  "WISpellColorful": 695070,
  "DA10HauntingControllerKeyword": 695065,
  "DaedricArtifact": 689768,
  "JewelryExpensive": 689764,
  "ClothingRich": 689757,
  "ClothingPoor": 689756,
  "ClothingBody": 689751,
  "LinkDragonOrbitMarker": 685747,
  "LinkDragonPerch3": 685746,
  "LinkDragonPerch2": 685745,
  "LinkDragonPerch1": 685744,
  "FurnitureForce3rdPerson": 677592,
  "FurnitureForce1stPerson": 677591,
  "GiftChildSpecial": 664716,
  "WE100ObjStart": 661427,
  "GiftPriestSpecial": 659045,
  "GiftThiefSpecial": 659044,
  "GiftWarriorSpecial": 659043,
  "GiftWizardSpecial": 659042,
  "GiftFletcherSpecial": 659041,
  "GiftApothecarySpecial": 659040,
  "GiftBlacksmithSpecial": 659039,
  "VendorItemScroll": 659031,
  "VendorItemFoodRaw": 659030,
  "GiftUniversallyValuable": 659029,
  "GiftFlower": 659028,
  "MagicTrapGas": 651918,
  "TGRQHouse": 650873,
  "LinkSoloPredator": 648837,
  "MQ306ShoutTarget": 647289,
  "SilverHandTarget": 644856,
  "ActorTypePrisoner": 641733,
  "IsTable": 637353,
  "ArmorShield": 615858,
  "VendorItemSpellTome": 604069,
  "VendorItemStaff": 604068,
  "VendorItemSoulGem": 604067,
  "VendorItemBook": 604066,
  "PerkFistsSteel": 604062,
  "AtT_NamedNode&NPC%SPC%Spine2%SPC%%LBR%Spn2%RBR%_NamedNode&MagicEffectsNode": 600684,
  "MQ304DevourDragon": 596720,
  "VendorItemDaedricArtifact": 595944,
  "VendorItemArrow": 595943,
  "WispChild03": 595564,
  "WispChild02": 595563,
  "WispChild01": 595562,
  "WispParent": 595561,
  "VendorItemKey": 595183,
  "VendorItemTool": 595182,
  "VendorItemGem": 595181,
  "VendorItemOreIngot": 595180,
  "VendorItemAnimalPart": 595179,
  "VendorItemAnimalHide": 595178,
  "VendorItemClutter": 595177,
  "PowerAttackTypeBack": 595176,
  "PowerAttackTypeSide": 595175,
  "PowerAttackTypeForward": 595174,
  "PowerAttackTypeStanding": 595173,
  "MQ304DevourEscape": 592474,
  "MQ304DevourWait": 592473,
  "MQ304DevourTarget": 592472,
  "VendorItemClothing": 588123,
  "VendorItemJewelry": 588122,
  "VendorItemArmor": 588121,
  "VendorItemWeapon": 588120,
  "CW5ForcedSpawn": 587854,
  "CW4ForcedSpawn": 587853,
  "CW3ForcedSpawn": 587852,
  "CW2ForcedSpawn": 587851,
  "CW1ForcedSpawn": 587850,
  "CWPotentialAllyImperial": 586502,
  "CWPotentialAllySons": 586501,
  "VendorItemPoison": 577005,
  "VendorItemPotion": 577004,
  "VendorItemIngredient": 577003,
  "VendorItemFood": 577002,
  "RitualSpellIllusion": 572306,
  "CompanionsSingleCombatEvent": 557299,
  "WRackStartingWeapon": 555458,
  "MagicTelekinesis": 521220,
  "MS08ArgueKeyword": 521212,
  "WRackShield": 515424,
  "CWAllPhases": 514336,
  "CW5Player": 466251,
  "CW4Player": 466247,
  "CW3Player": 466246,
  "CW2Player": 466244,
  "CW1Player": 466243,
  "WRackStaff": 465669,
  "WRackWaraxe": 465648,
  "WRackMace": 465646,
  "WRackSword": 465642,
  "CWPrepareCityStart": 346800,
  "DMPackageActivate": 321915,
  "MagicAlchHarmful": 271625,
  "MagicAlchRestoreMagicka": 271624,
  "MagicAlchRestoreStamina": 271620,
  "MagicAlchRestoreHealth": 271619,
  "PerkFistsIron": 271599,
  "MagicInfluenceCharm": 271598,
  "MagicInfluenceFear": 271584,
  "MagicSummonUndead": 149547,
  "MagicSummonShock": 149546,
  "MagicSummonFrost": 149545,
  "MagicSummonFire": 149539,
  "CraftingSmithingSharpeningWheel": 557320,
  "FurnitureResourceObjectSawmill": 557319,
  "FurnitureCounterLeanMarker": 557318,
  "CraftingSmithingForge": 557317,
  "CWFortSiegeStart": 556067,
  "LocTypeHoldMinor": 551139,
  "LocTypeHoldCapital": 551138,
  "LocTypeHoldMajor": 551137,
  "CW5": 527407,
  "CW4": 527406,
  "CW3": 527405,
  "CW2": 527404,
  "CW1": 527403,
  "RitualSpellEffect": 526049,
  "CWSiegeStart": 516908,
  "CWEscapeCityStart": 515323,
  "CW5PrioritySpawn": 513093,
  "CW4PrioritySpawn": 513092,
  "CW2PrioritySpawn": 513091,
  "CW1PrioritySpawn": 513090,
  "CW3PrioritySpawn": 513089,
  "CW5ActivateB": 509125,
  "CW4ActivateB": 509124,
  "CW3ActivateB": 509123,
  "CW2ActivateB": 509122,
  "CW5ActivateA": 509121,
  "CW4ActivateA": 509120,
  "CW3ActivateA": 509119,
  "CW2ActivateA": 509118,
  "CW1ActivateB": 509117,
  "CW1ActivateA": 509116,
  "CW5BreakBarricade": 506151,
  "CW4BreakBarricade": 506150,
  "CW3BreakBarricade": 506149,
  "CW2BreakBarricade": 506148,
  "CW1BreakBarricade": 506147,
  "MagicInfluence": 491672,
  "FreeformRiverwood01SceneKeyword": 485858,
  "CW5MissileClose": 426548,
  "CW5MissileWide": 426545,
  "CW5MeleeWide": 426523,
  "CW5MeleeClose": 426522,
  "CW4MissileWide": 426521,
  "CW4MissileClose": 426520,
  "CW4MeleeWide": 426519,
  "CW4MeleeClose": 426518,
  "CW3MissileWide": 426517,
  "CW3MissileClose": 426516,
  "CW3MeleeWide": 426515,
  "CW3MeleeClose": 426514,
  "CW2MissileWide": 426510,
  "CW2MissileClose": 426502,
  "CW2MeleeWide": 426501,
  "CW2MeleeClose": 426499,
  "CW1MissileClose": 426498,
  "CW1MissileWide": 426495,
  "CW1MeleeWide": 426493,
  "CW1MeleeClose": 426492,
  "WICommentDanger": 313042,
  "WICommentSetPiece": 312790,
  "WICommentEntrances": 312762,
  "TrapLink": 278566,
  "RelationshipMarriageFINKeyword": 136067,
  "RelationshipMarriageWeddingKeyword": 482496,
  "MagicEnchFortifyTwoHanded": 479091,
  "MagicEnchFortifyStaminaRate": 479090,
  "MagicEnchFortifyStamina": 479089,
  "MagicEnchFortifySpeechcraft": 479088,
  "MagicEnchFortifySneak": 479087,
  "MagicEnchFortifySmithing": 479086,
  "MagicEnchFortifyRestoration": 479085,
  "MagicEnchFortifyPickPocket": 479084,
  "MagicEnchFortifyOneHanded": 479083,
  "MagicEnchFortifyMass": 479082,
  "MagicEnchFortifyMarksman": 479081,
  "MagicEnchFortifyMagickaRate": 479080,
  "MagicEnchFortifyMagicka": 479079,
  "MagicEnchFortifyLockpicking": 479078,
  "MagicEnchFortifyLightArmor": 479077,
  "MagicEnchFortifyIllusion": 479076,
  "MagicEnchFortifyHeavyArmor": 479075,
  "MagicEnchFortifyHealth": 479074,
  "MagicEnchFortifyHealRate": 479073,
  "MagicEnchFortifyEnchanting": 479072,
  "MagicEnchFortifyDestruction": 479071,
  "MagicEnchFortifyConjuration": 479070,
  "MagicEnchFortifyCarryWeight": 479069,
  "MagicEnchFortifyBlock": 479068,
  "MagicEnchFortifyAlteration": 479067,
  "MagicEnchFortifyAlchemy": 479066,
  "MagicEnchResistShock": 479065,
  "MagicEnchResistMagic": 479064,
  "MagicEnchResistFrost": 479063,
  "MagicEnchResistFire": 479062,
  "MagicEnchWeaknessShock": 479061,
  "MagicEnchWeaknessMagic": 479060,
  "MagicEnchWeaknessFire": 479059,
  "MagicEnchWeaknessFrost": 479058,
  "MagicAlchWeaknessMagic": 479057,
  "MagicAlchWeaknessShock": 479056,
  "MagicAlchWeaknessFrost": 479055,
  "MagicAlchWeaknessFire": 479054,
  "RelationshipObjectionMaleKeyword": 478958,
  "RelationshipMarriageKeyword": 478759,
  "MarriageWeddingKeyword": 475937,
  "FurnitureWoodChoppingBlock": 470523,
  "WICrowdStart": 456951,
  "MagicNoReanimate": 456443,
  "MothNest2": 455678,
  "MothNest1": 455677,
  "FurnitureSpecial": 453063,
  "ActivatorLever": 450221,
  "WRackActivator": 448863,
  "WRackTrigger": 448862,
  "WeapTypeBattleaxe": 448818,
  "WeapTypeGreatsword": 448817,
  "WeapTypeWarhammer": 448816,
  "WISabotageStart": 446949,
  "WRackBow": 437191,
  "WRackWarhammer": 437188,
  "WRackBattleaxe": 437187,
  "WRackGreatsword": 437186,
  "ArmorGauntlets": 442607,
  "ArmorHelmet": 442606,
  "ArmorBoots": 442605,
  "ArmorCuirass": 442604,
  "ArmorJewelry": 441321,
  "ArmorClothing": 441320,
  "ArmorMaterialSteelPlate": 441319,
  "ArmorMaterialSteel": 441318,
  "ArmorMaterialOrcish": 441317,
  "ArmorMaterialIronBanded": 441316,
  "ArmorMaterialIron": 441315,
  "ArmorMaterialImperialHeavy": 441314,
  "ArmorMaterialImperialStudded": 441313,
  "ArmorMaterialImperialLight": 441312,
  "ArmorMaterialStudded": 441311,
  "ArmorMaterialScaled": 441310,
  "ArmorMaterialHide": 441309,
  "ArmorMaterialGlass": 441308,
  "ArmorMaterialLeather": 441307,
  "ArmorMaterialElvenGilded": 441306,
  "ArmorMaterialElven": 441305,
  "ArmorMaterialEbony": 441304,
  "ArmorMaterialDwarven": 441303,
  "ArmorMaterialDragonscale": 441302,
  "ArmorMaterialDragonplate": 441301,
  "ArmorMaterialDaedric": 441300,
  "ArmorLight": 441299,
  "ArmorHeavy": 441298,
  "CWLinkFortGuardMarker4": 441116,
  "CWLinkFortGuardMarker3": 441115,
  "CWLinkFortGuardMarker2": 441114,
  "CWLinkFortGuardMarker1": 441113,
  "CWLinkFortSleepNight": 441112,
  "CWLinkFortSleepDay": 441111,
  "CWCampsite": 423158,
  "CWMissionTutorialStart": 423146,
  "MagicAlchResistMagic": 416314,
  "MagicAlchResistShock": 416313,
  "MagicAlchResistFrost": 416312,
  "MagicAlchResistFire": 416311,
  "MagicAlchFortifyMass": 416310,
  "MagicAlchFortifyStaminaRate": 416309,
  "MagicAlchFortifyMagickaRate": 416308,
  "MagicAlchFortifyMagicka": 416307,
  "MagicAlchFortifyStamina": 416306,
  "MagicAlchFortifyHealth": 416305,
  "MagicAlchFortifyHealRate": 416304,
  "MagicAlchFortifyCarryWeight": 416303,
  "MagicAlchFortifyEnchanting": 416302,
  "MagicAlchFortifyRestoration": 416301,
  "MagicAlchFortifyIllusion": 416300,
  "MagicAlchFortifyDestruction": 416299,
  "MagicAlchFortifyConjuration": 416298,
  "MagicAlchFortifySpeechcraft": 416297,
  "MagicAlchFortifyAlchemy": 416296,
  "MagicAlchFortifySneak": 416295,
  "MagicAlchFortifyLockpicking": 416294,
  "MagicAlchFortifyPickPocket": 416293,
  "MagicAlchFortifyLightArmor": 416292,
  "MagicAlchFortifyHeavyArmor": 416291,
  "MagicAlchFortifySmithing": 416290,
  "MagicAlchFortifyMarksman": 416289,
  "MagicAlchFortifyTwoHanded": 416288,
  "MagicAlchFortifyOneHanded": 416287,
  "MagicAlchFortifyBlock": 416286,
  "MagicAlchFortifyAlteration": 416285,
  "MagicShout": 289689,
  "TGBusiness": 399433,
  "LinkCustom05": 382463,
  "LinkCustom04": 382462,
  "LinkCustom03": 382440,
  "LinkCustom02": 382439,
  "LinkCustom01": 382438,
  "LinkDragonPerch": 351211,
  "VoiceFireBreathLong": 374226,
  "VoiceFireBreathMedium": 374225,
  "VoiceFireBreathShort": 374223,
  "CWResetGarrisonStart8": 367465,
  "CWResetGarrisonStart7": 367464,
  "CWResetGarrisonStart6": 367463,
  "CWResetGarrisonStart5": 367462,
  "CWResetGarrisonStart2": 367454,
  "CWResetGarrisonStart4": 367453,
  "CWResetGarrisonStart3": 367452,
  "LinkDefPatrolDay": 364840,
  "LinkDefPatrolNight": 364839,
  "CWLinkWhiterun": 362464,
  "CWLinkGuardContested2": 362463,
  "CWLinkGuardContested3": 362462,
  "CWLinkGuardContested1": 362461,
  "LinkDefFollow": 357501,
  "LinkDefDay": 357043,
  "LinkDefNight": 357042,
  "LinkDefSandbox": 357041,
  "LinkDefPatrol": 357040,
  "LinkDefHold": 357039,
  "LinkDefGuard": 357038,
  "LinkDefWeaponDrawn": 357037,
  "LinkHuntingGround": 356929,
  "LinkLair": 356928,
  "LinkGuard3": 346018,
  "LinkGuard2": 346017,
  "LinkGuard1": 346016,
  "ActorTypeCow": 331966,
  "LocTypeStewardsDwelling": 328953,
  "CWAttackCityStart": 325824,
  "MQKillDragonKeyword": 130112,
  "WEStart": 304640,
  "FavorBrawlEvent": 293602,
  "RelationshipObjectionFemaleKeyword": 293412,
  "RelationshipCourtingKeyword": 293383,
  "MQCallDragonKeyword": 289672,
  "JobCourtWizard": 281163,
  "CWPurchasedByAttacker": 271911,
  "CWGarrisonNonContestable": 267327,
  "ArenaStartCombat": 265047,
  "CWFortOpenGateStart": 231304,
  "FavorFollowerEvent": 115694,
  "LocTypeHabitation": 235411,
  "JobPriest": 234017,
  "JobMisc": 232157,
  "CWGovernmentStart": 222774,
  "JobSpellVendor": 221626,
  "JobFletcher": 221625,
  "ActorTypeDragon": 220505,
  "TraitSympathizerSons": 210429,
  "TraitSympathizerImperial": 210428,
  "TraitPowerHungry": 210427,
  "TraitGreedy": 210426,
  "JobMiner": 209600,
  "JobSteward": 191459,
  "TownRadiantSR09": 182245,
  "TownRadiantSR11": 182239,
  "ActorTypeHorse": 155920,
  "JobOrcWiseWoman": 146904,
  "JobOrcChief": 146903,
  "CWResetGarrisonStart1": 145056,
  "CWResolution02Start": 135452,
  "MS01GuardAmbush": 135371,
  "TraitRich": 114676,
  "JobMinstrel": 183745,
  "JobApothecary": 183744,
  "JobHousecarl": 183743,
  "JobHostler": 183742,
  "JobJarl": 176988,
  "CWResolution01Start": 176755,
  "CWOwner": 173142,
  "CWCost": 173141,
  "MGRUrag": 166484,
  "MGRSergius": 166483,
  "MGRDrevis": 166482,
  "MGRTolfdir": 166481,
  "MGRContainer": 166466,
  "TGRadiantStartSL": 166197,
  "TGRadiantStartDU": 166196,
  "TGRadiantStartNT": 166195,
  "TGRadiantStartGF": 166194,
  "TGRadiantStartJB": 166193,
  "TGRadiantStartFO": 166192,
  "TGRadiantStartBE": 166191,
  "TGRadiantStartHC": 166190,
  "TGStore": 166188,
  "TGItemLarge": 166187,
  "TGWealthyHome": 166186,
  "TGValuable": 166185,
  "TGItemSmall": 166182,
  "TGMark": 166181,
  "CRFarkas": 152149,
  "CRVilkas": 152148,
  "CRSkjor": 152147,
  "CWCapitalHQ": 132589,
  "CWMissionStart": 132551,
  "MagicArmorSpell": 125554,
  "MagicParalysis": 125552,
  "MagicInvisibility": 125551,
  "MagicWard": 125545,
  "WeapMaterialDaedric": 124703,
  "WeapMaterialEbony": 124702,
  "WeapMaterialGlass": 124701,
  "WeapMaterialOrcish": 124700,
  "WeapMaterialElven": 124699,
  "WeapMaterialDwarven": 124698,
  "WeapMaterialSteel": 124697,
  "WeapMaterialIron": 124696,
  "WeapMaterialWood": 124695,
  "WeapTypeStaff": 124694,
  "WeapTypeBow": 124693,
  "WeapTypeMace": 124692,
  "WeapTypeDagger": 124691,
  "WeapTypeWarAxe": 124690,
  "WeapTypeSword": 124689,
  "JobHunter": 124666,
  "CWPatrol": 124610,
  "JobLumberjack": 121318,
  "JobFarmer": 121317,
  "CRAela": 118551,
  "MagicRestoreHealth": 118448,
  "MagicDamageShock": 118447,
  "MagicDamageFrost": 118446,
  "MagicDamageFire": 118445,
  "LocTypeShip": 118107,
  "LocTypeGuild": 118106,
  "LocTypeJail": 118105,
  "LocTypeCemetery": 118104,
  "LocTypeCastle": 118103,
  "LocTypeTemple": 118102,
  "LocTypeBarracks": 118101,
  "LocTypeInn": 117639,
  "LocTypeStore": 117638,
  "LocTypeHouse": 117637,
  "CWFort": 115879,
  "CWCampSons": 115878,
  "CWCampImperial": 115877,
  "CWGarrisonDefenderOnly": 115876,
  "CWGarrison": 115875,
  "CWCapital": 115874,
  "CWCampaignStart": 115190,
  "JobMerchant": 114082,
  "LocTypeShipwreck": 103071,
  "LocSetMilitaryCamp": 103018,
  "LocTypeLumberMill": 102130,
  "LocTypeMine": 102129,
  "LocTypeFarm": 102128,
  "LocTypeHold": 92017,
  "JobInnkeeper": 81673,
  "JobBlacksmith": 81672,
  "ActorTypeDwarven": 80250,
  "ActorTypeAnimal": 79768,
  "ActorTypeDaedra": 79767,
  "ActorTypeUndead": 79766,
  "ActorTypeCreature": 79765,
  "ActorTypeNPC": 79764,
  "LocTypeCity": 78184,
  "LocTypeSettlement": 78183,
  "LocTypeTown": 78182,
  "LocSetOutdoor": 78067,
  "LocSetNordicRuin": 78066,
  "LocSetMilitaryFort": 78065,
  "LocSetDwarvenRuin": 78064,
  "LocSetCave": 78063,
  "LocTypeForswornCamp": 78062,
  "LocTypeWerewolfLair": 78061,
  "LocTypeWarlockLair": 78060,
  "LocTypeVampireLair": 78059,
  "LocTypeSprigganGrove": 78058,
  "LocTypeOrcStronghold": 78057,
  "LocTypeMilitaryCamp": 78056,
  "LocTypeMilitaryFort": 78055,
  "LocTypeHagravenNest": 78054,
  "LocTypeGiantCamp": 78053,
  "LocTypeFalmerHive": 78052,
  "LocTypeDwarvenAutomatons": 78051,
  "LocTypeDraugrCrypt": 78050,
  "LocTypeDragonPriestLair": 78049,
  "LocTypeDragonLair": 78048,
  "LocTypeBanditCamp": 78047,
  "LocTypeAnimalDen": 78046,
  "LocTypeDwelling": 78044,
  "LocTypeDungeon": 78043,
  "TestDemoQuestgiver": 77565,
  "ccBGS_ActorTypeCustomPetResponse07_FollowfromWait": 16789657,
  "ccBGS_ActorTypeCustomPetResponse06_Wait": 16789656,
  "ccBGS_ActorTypeCustomPetResponse05_FollowfromDismissed": 16789655,
  "ccBGS_ActorTypeCustomPetResponse04_Trade": 16789654,
  "ccBGS_ActorTypeCustomPetResponse03_GoHome": 16789653,
  "ccBGS_ActorTypeCustomPetResponse02_Wait": 16789652,
  "ccBGS_ActorTypeCustomPetResponse01_Stay": 16789651,
  "CommandedVoiceExcluded": 16789588,
  "ccDisallowSaddleSwap": 16789397,
  "Survival_LocTypeFreeShrineUse": 16789212,
  "Survival_BodyAndHead": 16789211,
  "MagicFlameCloak": 16789210,
  "Survival_ArmorWarm": 16789209,
  "Survival_ArmorCold": 16789208,
  "ArmorMaterialBlades": 16779712,
  "ArmorMaterialThievesGuildLeader": 16779711,
  "ArmorMaterialBearStormcloak": 16779710,
  "ArmorMaterialFalmer": 16779709,
  "ArmorMaterialThievesGuild": 16779708,
  "ArmorMaterialPenitus": 16779707,
  "ArmorMaterialMS02Forsworn": 16779706,
  "ArmorMaterialForsworn": 16779705,
  "ImmuneDragonPairedKill": 16779682,
  "WEDL06Letrush": 16779679,
  "DA15WabbajackExcludedKeyword": 16779671,
  "DLC1VampireFeedBystanderStart": 33639611,
  "DLC1ArmorMaterialVampire": 33637950,
  "DLC1ProtectChange": 33637949,
  "DLC1DurnehviirKeyword": 33637836,
  "DLC1LinkUseWeaponRanged": 33636208,
  "DLC1LinkUseWeaponTarget": 33636206,
  "DLC1LinkUseWeaponMelee": 33636203,
  "DLC1ArmorMaterielFalmerHeavyOriginal": 33631440,
  "DLC1ArmorMaterielFalmerHeavy": 33631439,
  "DLC1ArmorMaterialFalmerHardened": 33631438,
  "DLC1ArmorMaterialDawnguard": 33631437,
  "ActorTypeDLC1Boss": 33629855,
  "DLC1ArvakExclusion": 33628732,
  "DLC1LinkEatLunchNight2": 33623900,
  "DLC1LinkEatLunchNight1": 33623899,
  "DLC1LinkEatDinnerNight2": 33623898,
  "DLC1LinkEatDinnerNight1": 33623897,
  "DLC1LinkEatBreakfastNight2": 33623896,
  "DLC1LinkEatBreakfastNight1": 33623895,
  "DLC1LD_ImmuneToAetherialShield": 33623703,
  "DLC1LDAetherialSummon": 33616767,
  "DLC1WispWall": 33614771,
  "DLC1VampireDrainEffect": 33609792,
  "DLC1DawnguardArmorShield": 33609791,
  "DLC1DawnguardArmorHelmet": 33609790,
  "DLC1DawnguardArmorGloves": 33609789,
  "DLC1DawnguardArmorBoots": 33609788,
  "DLC1DawnguardArmorBody": 33609787,
  "DLC1DawnguardItem": 33609785,
  "DLC1LegendaryDragon": 33607001,
  "DLC1LinkFeedTableThrall247": 33606997,
  "DLC1AurielsConditionalExplosionKeyword": 33606592,
  "DLC1WispWallEffect": 33575253,
  "DLC1WispWallWisp3": 33575252,
  "DLC1WispWallWisp2": 33575251,
  "DLC1WispWallWisp1": 33575250,
  "DLC1CrossbowIsEnhanced": 33569180,
  "DLC1RadiantHunterTechStart": 33566498,
  "DLC1LD_LavaImagespaceKeyword": 33565057,
  "DLC1ReadElderScroll": 33663322,
  "DLC1VampirePowersExclude": 33661728,
  "DLC1BthalftSoundLink": 33660310,
  "DLC1CoffinPuzzleBowl": 33659145,
  "DLC1WeapMaterialDragonbone": 33658914,
  "DLC1isVampireCoffinHorizontal": 33657642,
  "ActorTypeMount": 33657342,
  "DLC1VampireDetectLifeDispelKeyword": 33647064,
  "DLC1LinkFerrySeat2": 33646683,
  "DLC1LinkFerrySeat1": 33646682,
  "DLC1WerewolfFeedExclude": 33644499,
  "WeapDwarvenCrossbow": 33642898,
  "VampireEatingChair": 33642352,
  "isVampireFeastVictim": 33642349,
  "DLC1CrystalDrainKeyword": 33641514,
  "DLC1LD_LavaKeyword": 33641270,
  "DLC1LD_LavaLingeringKeyword": 33641269,
  "DLC1LD_SteamKeyword": 33641268,
  "DLC1LD_SteamLingeringKeyword": 33641267,
  "DLC1BloodPortal": 33640505,
  "DLC1VQ05SkeletonKeyword": 33640158,
  "FreeformRiverwood01SceneKeywordDUPLICATE001": 33640157,
  "DLC1BloodChaliceActivate": 33636755,
  "DLC1CraftingDawnguard": 33617926,
  "DLC1SeranaCoffin": 33617910,
  "DLC1LD_CraftingMaterialAetherium": 33612441,
  "DLC1VampReading": 33607805,
  "DLC01SoulHorseEnd": 33603032,
  "DLC01SoulHorseStart": 33603031,
  "DLC1isVampireCoffinVertical": 33601101,
  "ActorTypeVampireBrute": 33596107,
  "DLC1LD_Ghost": 33596084,
  "DLC1_ScrapeBarkKeyword": 33595996,
  "DLC1_WayShrineWaterScoopKeyword": 33595995,
  "DLC1_WayShrineWaterPourKeyWord": 33595994,
  "DLC1VampFeast": 33586578,
  "DLC1VampSpectateSpeech": 33586577,
  "DLC1VampSpectateTorture": 33586576,
  "DLC1HarkonFloorCenter": 33586575,
  "DLC1_SnowElfThroneKeyword": 33583200,
  "DLC1LD_CraftingForgeAetherium": 33576790,
  "DLC1RV03HunterGarb": 33575112,
  "DLC1ArmorMaterialHunter": 33575108,
  "DLC1RV03KillLocation": 33575106,
  "DLC1RadiantHunterStart": 33573918,
  "DLC1RadiantVampireStart": 33573917,
  "DLC1LinkGuard": 33567691,
  "DLC1LinkKeepEyeOn": 33567690,
  "DLC1LinkServices": 33567687,
  "DLC1LinkEatDinner2": 33567686,
  "DLC1LinkEatDinner1": 33567685,
  "DLC1LinkEatLunch2": 33567684,
  "DLC1LinkEatLunch1": 33567683,
  "DLC1LinkEatBreakfast2": 33567682,
  "DLC1LinkEatBreakfast1": 33567681,
  "DLC1LinkSandbox": 33567680,
  "DLC1LinkSleepDay3": 33567679,
  "DLC1LinkSleepDay2": 33567678,
  "DLC1LinkSleepDay1": 33567677,
  "DLC1LinkSleepNight3": 33567676,
  "DLC1LinkSleepNight2": 33567675,
  "DLC1LinkSleepNight1": 33567674,
  "BYOHBuildingInteriorPart206ShrineDibella": 50334553,
  "BYOHBuildingInteriorPart205TableNight01": 50334504,
  "BYOHBuildingInteriorPart204MountedHeadElkFemale01": 50334232,
  "BYOHBuildingInteriorPart203BookshelfTall06": 50334223,
  "BYOHBuildingInteriorPart202TableNightx2_02": 50334220,
  "BYOHBuildingInteriorPart201TableSquare02": 50334136,
  "BYOHBuildingInteriorPart200TableSquare01": 50334135,
  "BYOHBuildingInteriorPart199WallSconceExteriorx2": 50333968,
  "BYOHHouseBanditPacifierKeyword": 50333892,
  "BYOHBuildingInteriorPart198BedChild02": 50333719,
  "BYOHBuildingInteriorPart197BedChild01": 50333718,
  "BYOHHouseCraftingCategorySmithing": 50333703,
  "BYOHAdoptionHousepetKeyword": 50432888,
  "BYOHBuildingTrophyLink": 50431070,
  "BYOHBuildingInteriorPart196PracticeDummyChild01": 50430138,
  "BYOHCarpenterTable": 50414419,
  "BYOHCraftingOven": 50403319,
  "BYOHHouseSkeeverInfestationKeyword": 50399816,
  "BYOHCraftingDawnguard": 50395142,
  "BYOHBuildingInteriorPart195ShrineZenithar": 50394046,
  "BYOHBuildingInteriorPart194ShrineTalos": 50394045,
  "BYOHBuildingInteriorPart193ShrineMara": 50394044,
  "BYOHBuildingInteriorPart192ShrineAkatosh": 50394043,
  "BYOHBuildingInteriorPart191ShrineArkay": 50394042,
  "BYOHBuildingInteriorPart190ShrineStendarr": 50394041,
  "BYOHBuildingInteriorPart189ShrineKynareth": 50394040,
  "BYOHBuildingInteriorPart188ShrineJulianos": 50394039,
  "BYOHBuildingInteriorPart187ShrineBase01": 50394038,
  "BYOHBuildingInteriorPart186WallSconcex2_04": 50394037,
  "BYOHBuildingInteriorPart185VampireCoffin01": 50394036,
  "BYOHBuildingInteriorPart184MeadBarrelsx2_01": 50394035,
  "BYOHBuildingInteriorPart183WeaponRackx5_01": 50394034,
  "BYOHBuildingInteriorPart182Safex5_02": 50394033,
  "BYOHBuildingInteriorPart181Safex5_01": 50394032,
  "BYOHBuildingInteriorPart180Forge01": 50394031,
  "BYOHBuildingInteriorPart179Smelter01": 50394030,
  "BYOHBuildingInteriorPart178Barrels04": 50394029,
  "BYOHBuildingInteriorPart177Barrels03": 50394028,
  "BYOHBuildingInteriorPart176ArcheryTarget01": 50394027,
  "BYOHBuildingInteriorPart175MountedHeadBear02": 50394026,
  "BYOHBuildingInteriorPart174HangingRack04": 50393975,
  "BYOHBuildingInteriorPart173HangingRack03": 50393974,
  "BYOHBuildingInteriorPart172MountedHeadHorkerFireplace01": 50393971,
  "BYOHBuildingInteriorPart171Oven01": 50393969,
  "isChildSitOnKnees": 50392411,
  "isChildLayOnFloor": 50392409,
  "BYOHBuildingInteriorPart170MountedHeadGoat02": 50388364,
  "BYOHBuildingInteriorPart169TableNightx2_01": 50388362,
  "BYOHBuildingInteriorPart168PlanterLarge03": 50388343,
  "BYOHBuildingInteriorPart167PlanterLarge02": 50388342,
  "BYOHBuildingInteriorPart166PlanterLarge01": 50388341,
  "BYOHBuildingInteriorPart165PlanterSmall06": 50388340,
  "BYOHBuildingInteriorPart164PlanterSmall05": 50388339,
  "BYOHBuildingInteriorPart163PlanterSmall04": 50388338,
  "BYOHBuildingInteriorPart162PlanterSmall03": 50388337,
  "BYOHBuildingInteriorPart161PlanterSmall02": 50388336,
  "BYOHBuildingInteriorPart160PlanterSmall01": 50388335,
  "BYOHBuildingInteriorPart159MountedMudcrab02": 50388327,
  "BYOHAdoptionToyKeyword": 50386980,
  "BYOHAdoptionClothesKeyword": 50386979,
  "BYOHBuildingInteriorPart158ChestExterior01": 50385260,
  "BYOHBuildingInteriorPart157HangingRack02": 50384257,
  "BYOHBuildingInteriorPart156SafeWithShelf": 50384249,
  "BYOHBuildingInteriorPart155SafeWithShelf": 50384248,
  "BYOHBuildingInteriorPart154WallSconcex2_03": 50384247,
  "BYOHBuildingInteriorPart153Dresser02": 50384216,
  "BYOHBuildingInteriorPart152ArmorWorkbench01": 50384201,
  "BYOHBuildingInteriorPart151Grindstone01": 50384200,
  "BYOHBuildingInteriorPart150TanningRack01": 50384199,
  "BYOHBuildingInteriorPart149MannequinWithCupboard05": 50384195,
  "BYOHBuildingInteriorPart148MannequinWithCupboard04": 50384194,
  "BYOHBuildingInteriorPart147MannequinWithCupboard03": 50384193,
  "BYOHBuildingInteriorPart146MannequinWithCupboard02": 50384192,
  "BYOHBuildingInteriorPart145MannequinWithCupboard01": 50384191,
  "BYOHBuildingInteriorPart144WeaponRackx4_02": 50384185,
  "BYOHBuildingInteriorPart143WeaponRackx4_01": 50384184,
  "BYOHBuildingInteriorPart142DisplayCupboard02": 50384183,
  "BYOHBuildingInteriorPart141DisplayCupboard01": 50384182,
  "BYOHBuildingInteriorPart140LampStand02": 50384181,
  "BYOHBuildingInteriorPart139TableRound01": 50384180,
  "BYOHBuildingInteriorPart138BarrelsWithTable137": 50381330,
  "BYOHBuildingInteriorPart137TableEnd02": 50381329,
  "BYOHBuildingInteriorPart136WallShelvesx2_04": 50381328,
  "BYOHBuildingInteriorPart135WallShelvesx2_03": 50381327,
  "BYOHBuildingInteriorPart134ChestWithTable044": 50381321,
  "BYOHBuildingInteriorPart133ChestWithDisplayShelf039": 50381317,
  "BYOHBuildingInteriorPart132ChestWithTable130": 50381297,
  "BYOHBuildingInteriorPart131ChestWithTable130": 50381296,
  "BYOHBuildingInteriorPart130TableWithChest01": 50381293,
  "BYOHBuildingInteriorPart129SafeWithDisplayTable127": 50381291,
  "BYOHBuildingInteriorPart128ChestWithDisplayTable127": 50381290,
  "BYOHBuildingInteriorPart127DisplayTableLarge01": 50381289,
  "BYOHBuildingInteriorPart126ChairExterior01": 50378390,
  "BYOHBuildingInteriorPart125Mannequin01": 50378386,
  "BYOHBuildingInteriorPart124WallShelf01": 50378383,
  "BYOHBuildingInteriorPart123ChestWithCupboard020": 50378382,
  "BYOHBuildingInteriorPart122WeaponRackx3_01": 50378378,
  "BYOHBuildingInteriorPart121Brazier02": 50378375,
  "BYOHBuildingInteriorPart120Brazier01": 50378374,
  "BYOHBuildingInteriorPart119LampStand01": 50377953,
  "BYOHBuildingInteriorPart118WallSconce01": 50377952,
  "BYOHBuildingInteriorPart117BookshelfTall05": 50377951,
  "BYOHBuildingInteriorPart116BookshelfTall04": 50377950,
  "BYOHBuildingInteriorPart115BookshelfTall03": 50377949,
  "BYOHBuildingInteriorPart114BookshelfTall02": 50377948,
  "BYOHBuildingInteriorPart113BookshelfTall01": 50377947,
  "BYOHBuildingInteriorPart112Bookshelf04": 50377946,
  "BYOHBuildingInteriorPart111Bookshelf03": 50377945,
  "BYOHBuildingInteriorPart110Bookshelf02": 50377944,
  "BYOHBuildingInteriorPart109Cupboard04": 50376936,
  "BYOHBuildingInteriorPart108TrophyBaseLarge03": 50376935,
  "BYOHBuildingInteriorPart107TrophyBaseLarge02": 50376934,
  "BYOHBuildingInteriorPart106TrophyBaseLarge01": 50376933,
  "BYOHBuildingInteriorPart105TrophyBaseSmall04": 50376932,
  "BYOHBuildingInteriorPart104TrophyBaseSmall03": 50376931,
  "BYOHBuildingInteriorPart103TrophyBaseSmall02": 50376930,
  "BYOHBuildingInteriorPart102TrophyBaseSmall01": 50376929,
  "BYOHBuildingTrophyBase2": 50373404,
  "BYOHBuildingTrophyBase1": 50373403,
  "BYOHBuildingInteriorPart101Firepit01": 50373400,
  "BYOHBuildingInteriorPart100TableLow02": 50371484,
  "BYOHBuildingInteriorPart099MountedHeadElkMale02": 50371482,
  "BYOHBuildingInteriorPart098WeaponRackx2_02": 50371480,
  "BYOHBuildingInteriorPart097WeaponRackx2_01": 50371479,
  "BYOHBuildingInteriorPart096WallSconcex2_02": 50371478,
  "BYOHBuildingInteriorPart095TableLow01": 50371475,
  "BYOHBuildingInteriorPart094Bench01": 50371472,
  "BYOHBuildingInteriorPart093HangingRack01": 50371469,
  "BYOHBuildingInteriorPart092MountedSlaughterfishFireplace01": 50371468,
  "BYOHCavewormKeyword": 50369586,
  "BYOHBuildingInteriorPart091ChestWithBed198": 50368609,
  "BYOHBuildingInteriorPart090ChestWithBed197": 50368608,
  "BYOHHouseCraftingCategoryBuilding": 50367188,
  "BYOHHouseCraftingCategoryContainers": 50367171,
  "BYOHHouseCraftingCategoryWeaponRacks": 50367170,
  "BYOHHouseCraftingCategoryShelf": 50367169,
  "BYOHHouseCraftingCategoryFurniture": 50367168,
  "BYOHBuildingInteriorPart089ArcheryTargetx2Exterior01": 50367164,
  "BYOHBuildingInteriorPart088TanningRackExterior01": 50367163,
  "BYOHBuildingInteriorPart087TableSquareExterior01": 50367162,
  "BYOHBuildingInteriorPart086TableRoundChairsExterior01": 50367158,
  "BYOHBuildingInteriorPart085WashbasinExterior01": 50367148,
  "BYOHBuildingInteriorPart084BenchExterior03": 50367147,
  "BYOHBuildingInteriorPart083BenchExterior02": 50367146,
  "BYOHBuildingInteriorPart082BenchExterior01": 50367145,
  "BYOHBuildingInteriorPart081TableLowExterior03": 50367144,
  "BYOHBuildingInteriorPart080TableLowExterior02": 50367143,
  "BYOHBuildingInteriorPart079TableLowExterior01": 50367142,
  "BYOHBuildingInteriorPart078TableBenchesExterior01": 50367133,
  "BYOHHouseCraftingCategoryExterior": 50367131,
  "BYOHBuildingInteriorPart077WallSconcex2_01": 50365524,
  "BYOHBuildingInteriorPart076MountedHeadBear01": 50365523,
  "BYOHBuildingInteriorPart075ShelfSmall01": 50365522,
  "BYOHBuildingInteriorPart074Chest03": 50365521,
  "BYOHBuildingInteriorPart073Barrels02": 50355806,
  "BYOHBuildingInteriorPart072Barrels01": 50355805,
  "BYOHBuildingInteriorPart047WallShelvesx4_02": 50354736,
  "BYOHBuildingInteriorPart059ChandelierSmall02": 50354706,
  "BYOHBuildingInteriorPart044TableEnd01": 50354705,
  "BYOHBuildingInteriorPart067MountedHeadWolf02": 50354704,
  "BYOHBuildingInteriorPart066MountedHeadWolf01": 50354703,
  "BYOHBuildingInteriorPart070MountedSlaughterfish02": 50354702,
  "BYOHBuildingInteriorPart069MountedSlaughterfish01": 50354701,
  "BYOHBuildingInteriorPart065MountedHeadSabreCat02": 50354700,
  "BYOHBuildingInteriorPart064MountedHeadSabreCat01": 50354699,
  "BYOHBuildingInteriorPart068MountedMudcrab01": 50354698,
  "BYOHBuildingInteriorPart063MountedHeadHorker01": 50354697,
  "BYOHBuildingInteriorPart062MountedHeadGoat01": 50354696,
  "BYOHBuildingInteriorPart061MountedHeadElkMale01": 50354695,
  "BYOHBuildingInteriorPart060MountedHeadElkAntlers01": 50354694,
  "BYOHBuildingInteriorPart058ChandelierSmall01": 50354693,
  "BYOHBuildingInteriorPart057ChandelierLarge01": 50354692,
  "BYOHBuildingInteriorPart055DisplayTableLow02": 50354691,
  "BYOHBuildingInteriorPart054WeaponRackSingle01": 50354690,
  "BYOHBuildingInteriorPart053WardrobeTall03": 50354689,
  "BYOHBuildingInteriorPart052TableEndx2_01": 50354688,
  "BYOHBuildingInteriorPart051DisplayWardrobeSmall02": 50354687,
  "BYOHBuildingInteriorPart050WardrobeTall02": 50354686,
  "BYOHBuildingInteriorPart049Chair03": 50354685,
  "BYOHBuildingInteriorPart046ChestLongWithBed01": 50354684,
  "BYOHBuildingInteriorPart042Dresser01": 50354683,
  "BYOHBuildingInteriorPart041Cupboard03": 50354682,
  "BYOHBuildingInteriorPart040Cupboard02": 50354681,
  "BYOHBuildingInteriorPart039DisplayShelf01": 50354680,
  "BYOHBuildingInteriorPart033EnchantingTable01": 50354679,
  "BYOHBuildingInteriorPart032WardrobeTall01": 50354678,
  "BYOHBuildingInteriorPart030Desk02": 50354677,
  "BYOHBuildingInteriorPart031DisplayCase02": 50354676,
  "BYOHBuildingInteriorPart027DisplayCase01": 50354675,
  "BYOHBuildingInteriorPart025WardrobeSmall02": 50354674,
  "BYOHBuildingInteriorPart035ShelfCorner02": 50354673,
  "BYOHBuildingInteriorPart023ShelfCorner01": 50354672,
  "BYOHBuildingInteriorPart020Cupboard01": 50354671,
  "BYOHBuildingInteriorPart018WardrobeSmall01": 50354670,
  "BYOHBuildingInteriorPart019DisplayWardrobeSmall01": 50354669,
  "BYOHBuildingInteriorPart017Anvil01": 50354668,
  "BYOHBuildingInteriorPart016Safe01": 50354667,
  "BYOHBuildingInteriorPart015Desk01": 50354666,
  "BYOHBuildingInteriorPart014WeaponPlaquex2_01": 50354665,
  "BYOHBuildingInteriorPart034WeaponPlaque02": 50354664,
  "BYOHBuildingInteriorPart024WeaponPlaque01": 50354663,
  "BYOHBuildingInteriorPart022WallShelvesx4_01": 50354662,
  "BYOHBuildingInteriorPart038WallShelvesx3": 50354661,
  "BYOHBuildingInteriorPart021WallShelvesx2_02": 50354660,
  "BYOHBuildingInteriorPart056ShelfTall05": 50354659,
  "BYOHBuildingInteriorPart048Bookshelf01": 50354658,
  "BYOHBuildingInteriorPart043ShelfTallDisplayCase01": 50354657,
  "BYOHBuildingInteriorPart026ShelfTall02": 50354656,
  "BYOHBuildingInteriorPart013ShelfTall01": 50354655,
  "BYOHBuildingInteriorPart012TableSquareChairs03": 50354654,
  "BYOHBuildingInteriorPart011TableRoundChairs01": 50354653,
  "BYOHBuildingInteriorPart010Washbasin01": 50354652,
  "BYOHBuildingInteriorPart009AlchemyTable01": 50354651,
  "BYOHBuildingInteriorPart008DisplayTableLow01": 50354650,
  "BYOHBuildingInteriorPart007Chest02": 50354649,
  "BYOHBuildingInteriorPart006Chest01": 50354648,
  "BYOHBuildingInteriorPart005TableSquareChairs02": 50354647,
  "BYOHBuildingInteriorPart003WallShelvesx2_01": 50354645,
  "BYOHBuildingInteriorPart045BedDouble01": 50354644,
  "BYOHBuildingInteriorPart002DiningTableChairs01": 50354643,
  "BYOHHouseBanditAttackKeyword": 50352651,
  "BYOH_LocTypeHomestead": 50351447,
  "BYOHBuildingInteriorPart071UNUSED": 50346904,
  "BYOHAdoptionStewardCourierEvent": 50347897,
  "BYOHAdoptionNewAdoptionEvent": 50347885,
  "BYOHBuildingInteriorPart004TableSquareChairs01": 50344202,
  "BYOHBuildingInteriorPart037BedSingle02": 50344164,
  "BYOHBuildingInteriorPart036BedSingle01": 50344163,
  "BYOHBuildingInteriorPart029Chair02": 50344162,
  "BYOHBuildingInteriorPart028Chair01": 50344161,
  "BYOHBuildingInteriorPart001Fireplace01": 50344158,
  "BYOHHouseLocationKeyword": 50344077,
  "BYOHBuildingDrafting": 50344028,
  "BYOHBuildingCarpenter": 50343957,
  "isCraftingOven": 50341952,
  "DLC2DremoraButlerKeyword": 67232174,
  "DLC2MorasGraspExcludedKeyword": 67359481,
  "DLC2FreaSorrow": 67359419,
  "isDLC02MiraakDeath": 67359300,
  "DLC2LinkBlackBookSound": 67359266,
  "DLC2ActorTypeMiraak": 67357336,
  "isTowerFloatDown": 67348032,
  "DLC2IsPickaxeWall": 67347600,
  "DLC2IsPickaxeTable": 67347599,
  "DLC2IsPickaxeFloor": 67347598,
  "DLC2LinkBlackBookEnabled": 67347422,
  "DLC2NordicPickaxe": 67347253,
  "DLC2MagicAshSpawn": 67347245,
  "DLC2ArmorMaterialMoragTong": 67347240,
  "DLC2RieklingMountedKeyword": 67346777,
  "DLC2RieklingKeyword": 67346776,
  "DLC2NetchKeyword": 67346775,
  "isTowerFloatUp": 67345592,
  "isDLC02TentacleWordBurn": 67345320,
  "MagicIgnite": 67340984,
  "DLC2LinkAshSpawnAttackHoldPosition": 67339322,
  "DLC2dunHaknirScimitar02Keyword": 67338322,
  "DLC2dunHaknirScimitar01Keyword": 67338320,
  "DLC2TTR5SpecialSpell": 67332712,
  "DLC2WerebearKeyword": 67325879,
  "StonePickUp": 67325686,
  "DLC2MagicMorasAgony": 67320224,
  "DLC2MH02ThirskRieklingForceGreeter": 67319779,
  "isRieklingDance": 67318374,
  "isRieklingPray": 67315494,
  "DLC2StandingStoneFXLink": 67312700,
  "isRieklingChisel": 67312399,
  "isRieklingThrone": 67312398,
  "DLC2_isChildLayOnFloor": 67310656,
  "DLC2_isChildSitOnKnees": 67310654,
  "LocTypeWerebearLair": 67291498,
  "DLC2LocTypeAshSpawn": 67291497,
  "DLC2LinkPillarMonster": 67287731,
  "DLC2CraftingSmithingSkaalForge": 67285107,
  "DLC2BenthicLurkerSpray": 67283167,
  "isKneelingChisel": 67282642,
  "isStandingChisel": 67280174,
  "DLC2LocTypeRieklingCamp": 67278638,
  "DLC2AshSpawnKeyword": 67276766,
  "DLC2LinkPillarStandingStone": 67274346,
  "DLC2LinkPillarMonsterSpawn": 67274345,
  "DLC2PillarDestroyedStart": 67274341,
  "DLC2SV02AncarionMerchantKeyword": 67272212,
  "DLC2dunKolbjornAhzidalItem": 67268839,
  "DLC2WeaponMaterialNordic": 67265072,
  "DLC2WeaponMaterialStalhrim": 67265071,
  "DLC2ArmorMaterialStalhrimLight": 67256583,
  "DLC2ArmorMaterialStalhrimHeavy": 67256582,
  "DLC2ArmorMaterialNordicHeavy": 67256581,
  "DLC2ArmorMaterialNordicLight": 67256580,
  "DLC2ArmorMaterialChitinHeavy": 67256579,
  "DLC2ArmorMaterialChitinLight": 67256578,
  "DLC2ArmorMaterialBonemoldHeavy": 67256577,
  "DLC2ArmorMaterialBonemoldLight": 67256576,
  "DLC2dunHaknirArmor": 67256354,
  "DLC2LocTypePillar": 67231421,
  "DLC2LinkPillarToggle": 67231419,
  "DLC2ApocryphaBookLink": 67222913,
  "DLC2DragonMountKeyword": 67222909,
  "DLC2WEStart": 67217963,
  "DLC2WERoadStart": 67217962,
  "DLC2TT2HeartStoneKeyword": 67212831,
  "testPhilCraftingBreakItDowner": 67210417,
  "DLC2StaffEnchanter": 67204920,
  "aaMZkw_TriggerBoxRanch": 85692686,
  "aaMZkw_TriggerBoxField": 85692688,
  "aaMZkw_MineOre_Table": 84676518,
  "aaMZkw_MineOre_Wall": 84676519,
  "IsBuyRanch": 85526786,
  "aaMZkw_MineOre_Orichalcum": 86107531,
  "isBuyCow": 85526790,
  "aaMZkw_CookingSpot": 85900138,
  "isSpawnAnimalPoint": 85526794,
  "aaMZkw_MineOre_Iron": 86107517,
  "aaMZkw_OreIronSilverOrichalcum": 86003833,
  "aaMZkw_CuttingBoard": 83991886,
  "ZoneRanch": 85526795,
  "aaMZkw_MineOre_Floor": 84676517,
  "aaMZkw_MineOre_Corundum": 86107524
}